MANIFEST.in
README.rst
setup.py
alto/__init__.py
alto/middleware.py
alto/parser.py
alto/templates.py
alto/urls.py
alto/urlviz.py
alto/views.py
alto.egg-info/PKG-INFO
alto.egg-info/SOURCES.txt
alto.egg-info/dependency_links.txt
alto.egg-info/requires.txt
alto.egg-info/top_level.txt
alto/static/bootstrap/css/bootstrap-responsive.css
alto/static/bootstrap/css/bootstrap-responsive.min.css
alto/static/bootstrap/css/bootstrap.css
alto/static/bootstrap/css/bootstrap.min.css
alto/static/bootstrap/img/glyphicons-halflings-white.png
alto/static/bootstrap/img/glyphicons-halflings.png
alto/static/bootstrap/js/bootstrap.js
alto/static/bootstrap/js/bootstrap.min.js
alto/static/codemirror/LICENSE
alto/static/codemirror/README.md
alto/static/codemirror/index.html
alto/static/codemirror/package.json
alto/static/codemirror/demo/activeline.html
alto/static/codemirror/demo/changemode.html
alto/static/codemirror/demo/closetag.html
alto/static/codemirror/demo/complete.html
alto/static/codemirror/demo/emacs.html
alto/static/codemirror/demo/folding.html
alto/static/codemirror/demo/formatting.html
alto/static/codemirror/demo/fullscreen.html
alto/static/codemirror/demo/loadmode.html
alto/static/codemirror/demo/marker.html
alto/static/codemirror/demo/matchhighlighter.html
alto/static/codemirror/demo/multiplex.html
alto/static/codemirror/demo/mustache.html
alto/static/codemirror/demo/preview.html
alto/static/codemirror/demo/resize.html
alto/static/codemirror/demo/runmode.html
alto/static/codemirror/demo/search.html
alto/static/codemirror/demo/theme.html
alto/static/codemirror/demo/vim.html
alto/static/codemirror/demo/visibletabs.html
alto/static/codemirror/doc/baboon.png
alto/static/codemirror/doc/baboon_vector.svg
alto/static/codemirror/doc/compress.html
alto/static/codemirror/doc/docs.css
alto/static/codemirror/doc/internals.html
alto/static/codemirror/doc/manual.html
alto/static/codemirror/doc/oldrelease.html
alto/static/codemirror/doc/reporting.html
alto/static/codemirror/doc/upgrade_v2.2.html
alto/static/codemirror/keymap/emacs.js
alto/static/codemirror/keymap/vim.js
alto/static/codemirror/lib/codemirror.css
