Metadata-Version: 1.0
Name: alto
Version: 0.4
Summary: A high-level code browser for Django projects.
Home-page: http://github.com/jkocherhans/alto
Author: Joseph Kocherhans
Author-email: joseph@jkocherhans.com
License: BSD
Platform: UNKNOWN
Classifier: Development Status :: 3 - Alpha
Classifier: Environment :: Web Environment
Classifier: Framework :: Django
Classifier: Intended Audience :: Developers
Classifier: License :: OSI Approved :: BSD License
Classifier: Operating System :: OS Independent
Classifier: Programming Language :: Python
Classifier: Programming Language :: Python :: 2.7
